ismk/__init__.py
ismk/__main__.py
ismk/_interface_alias.py
ismk/_version.py
ismk/api.py
ismk/assets/__init__.py
ismk/assets/data/@types-clone/LICENSE
ismk/assets/data/@types-estree/LICENSE
ismk/assets/data/array-flat-polyfill/LICENSE
ismk/assets/data/clone/LICENSE
ismk/assets/data/commons-math/LICENSE.txt
ismk/assets/data/commons-math/NOTICE.txt
ismk/assets/data/d3-array/LICENSE
ismk/assets/data/d3-color/LICENSE
ismk/assets/data/d3-contour/LICENSE
ismk/assets/data/d3-delaunay/LICENSE
ismk/assets/data/d3-dispatch/LICENSE
ismk/assets/data/d3-dsv/LICENSE
ismk/assets/data/d3-force/LICENSE
ismk/assets/data/d3-format/LICENSE
ismk/assets/data/d3-geo/LICENSE
ismk/assets/data/d3-geo-projection/LICENSE
ismk/assets/data/d3-hierarchy/LICENSE
ismk/assets/data/d3-interpolate/LICENSE
ismk/assets/data/d3-path/LICENSE
ismk/assets/data/d3-quadtree/LICENSE
ismk/assets/data/d3-regression/LICENSE
ismk/assets/data/d3-scale/LICENSE
ismk/assets/data/d3-shape/LICENSE
ismk/assets/data/d3-time/LICENSE
ismk/assets/data/d3-time-format/LICENSE
ismk/assets/data/d3-timer/LICENSE
ismk/assets/data/delaunator/LICENSE
ismk/assets/data/esprima/LICENSE.BSD
ismk/assets/data/fabric/LICENSE
ismk/assets/data/fast-deep-equal/LICENSE
ismk/assets/data/fast-json-patch/LICENSE
ismk/assets/data/fast-json-stable-stringify/LICENSE
ismk/assets/data/hashlru/LICENSE
ismk/assets/data/heroicons/LICENSE
ismk/assets/data/json-stringify-pretty-compact/LICENSE
ismk/assets/data/prop-types/LICENSE
ismk/assets/data/prop-types/prop-types.min.js
ismk/assets/data/pygments/LICENSE
ismk/assets/data/quickselect/LICENSE
ismk/assets/data/react/LICENSE
ismk/assets/data/react/react-dom.production.min.js
ismk/assets/data/react/react.production.min.js
ismk/assets/data/regression/LICENSE
ismk/assets/data/science/LICENSE
ismk/assets/data/semver/LICENSE
ismk/assets/data/shapefile/LICENSE
ismk/assets/data/snakemake/LICENSE.md
ismk/assets/data/tailwindcss/LICENSE
ismk/assets/data/tailwindcss/tailwind.css
ismk-2025.12.18.dist-info/WHEEL
ismk-2025.12.18.dist-info/entry_points.txt
ismk-2025.12.18.dist-info/METADATA
ismk-2025.12.18.dist-info/RECORD
